djangoshop_wspay-0.1.0.dist-info/DESCRIPTION.rst
djangoshop_wspay-0.1.0.dist-info/LICENSE.txt
djangoshop_wspay-0.1.0.dist-info/METADATA
djangoshop_wspay-0.1.0.dist-info/RECORD
djangoshop_wspay-0.1.0.dist-info/WHEEL
djangoshop_wspay-0.1.0.dist-info/metadata.json
djangoshop_wspay-0.1.0.dist-info/top_level.txt
shop_wspay/__init__.py
shop_wspay/forms.py
shop_wspay/modifiers.py
shop_wspay/payment.py
shop_wspay/settings.py
shop_wspay/templates/shop_wspay/cancel.html
shop_wspay/templates/shop_wspay/error.html
shop_wspay/templates/shop_wspay/failed.html
shop_wspay/templates/shop_wspay/payment.html
